<?xml version="1.0"?>
<GUI Try="Try" GridLines="8" EditCol="0|0|0" RowColor="15790320|16777215|12648447|11861980|16777152|16761087" IndicatorColor="255|15790320|16711680|0" Class="FitLinear" ClassOptionName="FitLinear" AdvanThemeFile="FitLinear" ExecMode="1" HelpID="4300" DialogDisplay="1" ThemeFile="" ComboChanged="125"><AutoUpdate NodeID="13" Label="Recalculate" DataID="15" Enable="1" DB_CTRL_ID="6000">2</AutoUpdate><Separator NodeID="77" DB_CTRL_ID="6002"/><DialogSettings Show="0" Label="DSParam1" DB_CTRL_ID="6003"><DSParam1 DataID="14" DB_CTRL_ID="6004">0</DSParam1></DialogSettings><InputData NodeID="44" Label="Input Data" DataID="2097163" Branch="1" DataMode="3" ThemeApplicabilityEx="-2146172928" Use="0" BranchCombo="Independent Fit - Consolidated Report|Independent Fit - Separate Report|Concatenate Fit|Global Fit" ActionFilterTags="FitCurve" HandlerRC="566248672" InteractiveOptions="32" _EntireWorksheet="0" DataRules="5509120" ChangeParam="0" DB_CTRL_ID="6006"><Range1 NodeID="39" PlotObjUID="1355"><X NodeID="35">[Book1]Sheet1!A</X><Y NodeID="35">[Book1]Sheet1!D</Y><ED NodeID="35">[Book1]Sheet1!C</ED></Range1></InputData><Order NodeID="17" Label="Polynomial Order" DataID="194" Show="0" DB_CTRL_ID="6007">2.</Order><Fit NodeID="268435456" Label="Fit Options" DataID="2097205" Branch="2049" DB_CTRL_ID="6009"><ErrBarWeight NodeID="13" Label="Errors as Weight" DataID="205" Handler="311961984" DB_CTRL_ID="6010" Enable="1">2.</ErrBarWeight><YWeight NodeID="13" Label="Y Weighting Method" DataID="1300" Show="0" DB_CTRL_ID="6012">0.</YWeight><XWeight NodeID="13" Label="X Weighting Method" DataID="1305" Show="0" DB_CTRL_ID="6014">0.</XWeight><FixIntercept NodeID="10" Label="Fix Intercept" DataID="225" Handler="311967360" DB_CTRL_ID="6016">0.</FixIntercept><FixInterceptAt NodeID="14" Label="Fix Intercept at" DataID="230" DB_CTRL_ID="6018" Enable="0">0.</FixInterceptAt><FixSlope NodeID="10" Label="Fix Slope" DataID="195" Handler="311970560" DB_CTRL_ID="6020">0.</FixSlope><FixSlopeAt NodeID="14" Label="Fix Slope at" DataID="200" DB_CTRL_ID="6022" Enable="0">1.</FixSlopeAt><UseReducedChiSq NodeID="10" Label="Use Reduced Chi-Sqr" DataID="210" DB_CTRL_ID="6024" Enable="1">1.</UseReducedChiSq><ApparentFit NodeID="10" Label="Apparent Fit" DataID="220" Handler="311975040" DB_CTRL_ID="6026" Enable="1">1.</ApparentFit></Fit><Quantities NodeID="268435456" Label="Quantities to Compute" DataID="2097170" Branch="2048" DB_CTRL_ID="6028"><Parameters NodeID="268435456" Label="Fit Parameters" DataID="2097169" Branch="526336" DB_CTRL_ID="6029"><Value NodeID="10" Label="Value" Label_E="Value" DataID="320" DB_CTRL_ID="6030">1.</Value><Shared NodeID="10" Label="Shared" Label_E="Shared" DataID="323" Show="0" DB_CTRL_ID="6032">0.</Shared><Fix NodeID="10" Label="Fixed" Label_E="Fixed" DataID="322" Show="0" DB_CTRL_ID="6034">0.</Fix><Error NodeID="10" Label="Standard Error" Label_E="Standard Error" DataID="321" DB_CTRL_ID="6036">1.</Error><LCL NodeID="10" Label="LCL" Label_E="LCL" DataID="330" HandlerRC="566342624" DB_CTRL_ID="6038">0.</LCL><UCL NodeID="10" Label="UCL" Label_E="UCL" DataID="331" HandlerRC="566342624" DB_CTRL_ID="6040">0.</UCL><Confidence NodeID="14" Label="Confidence Level for Parameters(%)" DataID="215" HandlerRC="566342624" DB_CTRL_ID="6042" Enable="0">95.</Confidence><tValue NodeID="10" Label="t-Value" Label_E="t-Value" DataID="325" DB_CTRL_ID="6044">0.</tValue><Prob NodeID="10" Label="Prob&gt;|t|" Label_E="Prob&gt;|t|" DataID="334" DB_CTRL_ID="6046">0.</Prob><Dependency NodeID="10" Label="Dependency" Label_E="Dependency" DataID="337" Show="0" DB_CTRL_ID="6048">0.</Dependency><ConfInterval NodeID="10" Label="CI Half-Width" Label_E="CI Half-Width" DataID="338" DB_CTRL_ID="6050">0.</ConfInterval></Parameters><Statistics NodeID="268435456" Label="Fit Statistics" DataID="2097168" Branch="2623488" DB_CTRL_ID="6052"><N NodeID="10" Label="Number of Points" Label_E="Number of Points" DataID="350" DB_CTRL_ID="6053">1.</N><DOF NodeID="10" Label="Degrees of Freedom" Label_E="Degrees of Freedom" DataID="351" DB_CTRL_ID="6055">1.</DOF><ReducedChiSq NodeID="10" Label="Reduced Chi-Sqr" Label_E="Reduced Chi-Sqr" DataID="366" DB_CTRL_ID="6057">0</ReducedChiSq><Rvalue NodeID="10" Label="R Value" Label_E="R Value" DataID="352" DB_CTRL_ID="6059">0.</Rvalue><SSR NodeID="10" Label="Residual Sum of Squares" Label_E="Residual Sum of Squares" DataID="367" DB_CTRL_ID="6061">1.</SSR><Correlation NodeID="10" Label="Pearson's r" Label_E="Pearson's r" DataID="370" DB_CTRL_ID="6063">1.</Correlation><RSqCOD NodeID="10" Label="R-Square(COD)" Label_E="R-Square(COD)" DataID="355" DB_CTRL_ID="6065">0.</RSqCOD><AdjRSq NodeID="10" Label="Adj. R-Square" Label_E="Adj. R-Square" DataID="356" DB_CTRL_ID="6067">1.</AdjRSq><RMSESD NodeID="10" Label="Root-MSE (SD)" Label_E="Root-MSE (SD)" DataID="360" DB_CTRL_ID="6069">0.</RMSESD><NormResiduals NodeID="10" Label="Norm of Residuals" Label_E="Norm of Residuals" DataID="380" DB_CTRL_ID="6071">0.</NormResiduals><NumIter NodeID="10" Label="Number of Iterations" Label_E="Number of Iterations" DataID="382" Show="0" DB_CTRL_ID="6073">0.</NumIter><FitStatus NodeID="10" Label="Fit Status" Label_E="Fit Status" DataID="384" Show="0" DB_CTRL_ID="6075">1.</FitStatus><ReplicaNum NodeID="10" Label="Number of Replicas" Label_E="Number of Replicas" DataID="385" Show="0" DB_CTRL_ID="6077">0.</ReplicaNum><ParamsFromNum NodeID="10" Label="Replicate From nth Parameter" Label_E="Replicate From nth Parameter" DataID="386" Show="0" DB_CTRL_ID="6079">0.</ParamsFromNum><ParamsUsed NodeID="10" Label="Number of Parameters Used in Replicas" Label_E="Number of Parameters Used in Replicas" DataID="387" Show="0" DB_CTRL_ID="6081">0.</ParamsUsed></Statistics><SummaryTable NodeID="268435456" Label="Fit Summary" DataID="342" Use="1" DB_CTRL_ID="6083"><Value NodeID="10" Label="Value" Label_E="Value" DataID="343" DB_CTRL_ID="6084">1.</Value><Error NodeID="10" Label="Standard Error" Label_E="Standard Error" DataID="344" DB_CTRL_ID="6086">1.</Error><LCL NodeID="10" Label="LCL" Label_E="LCL" DataID="345" DB_CTRL_ID="6088">0.</LCL><UCL NodeID="10" Label="UCL" Label_E="UCL" DataID="346" DB_CTRL_ID="6090">0.</UCL><AdjRSq NodeID="10" Label="Adj. R-Square" Label_E="Adj. R-Square" DataID="347" DB_CTRL_ID="6092">1.</AdjRSq><RSqCOD NodeID="10" Label="R-Square(COD)" Label_E="R-Square(COD)" DataID="348" DB_CTRL_ID="6094">0.</RSqCOD><ReducedChiSq NodeID="10" Label="Reduced Chi-Sqr" Label_E="Reduced Chi-Sqr" DataID="349" Show="0" DB_CTRL_ID="6096">0</ReducedChiSq></SummaryTable><ANOVAtable NodeID="10" Label="ANOVA" Label_E="ANOVA" DataID="475" DB_CTRL_ID="6098">1.</ANOVAtable><mCov NodeID="10" Label="Covariance matrix" Label_E="Covariance matrix" DataID="170" DB_CTRL_ID="6100">0.</mCov><mCor NodeID="10" Label="Correlation matrix" Label_E="Correlation matrix" DataID="171" DB_CTRL_ID="6102">0.</mCor></Quantities><ResAnalysis NodeID="268435456" Label="Residual Analysis" DataID="2097217" Branch="2623488" DB_CTRL_ID="6104"><Regular NodeID="10" Label="Regular" DataID="3951" DB_CTRL_ID="6105">1.</Regular><Stad NodeID="10" Label="Standardized" DataID="3952" DB_CTRL_ID="6107" Enable="0">0</Stad><Stud NodeID="10" Label="Studentized" DataID="3953" DB_CTRL_ID="6109" Enable="0">0</Stud><StudDel NodeID="10" Label="Studentized Deleted" DataID="3954" DB_CTRL_ID="6111" Enable="0">0</StudDel></ResAnalysis><Output NodeID="268435456" Label="Output Settings" DataID="2097488" Branch="2048" ChangeParam="0" DB_CTRL_ID="6113"><PlotSettings NodeID="268435456" Label="Graph Arrangement" DB_CTRL_ID="6114"><PasteResultTable NodeID="268435456" Label="Paste Result Tables to Source Graph" Use="1" DataID="940" Show="1" DB_CTRL_ID="6115" Enable="1"><TableTemplate NodeID="11" Label="Template to Create Table" DataID="1549" DB_CTRL_ID="6116"/><ThemeRsltTable NodeID="11" Label="Graph Table Theme" DataID="1558" DB_CTRL_ID="6118"/></PasteResultTable><GraphNumCols NodeID="14" Label="Arrange Graphs into Columns" DataID="4000" Auto="1||1" DB_CTRL_ID="6120">1</GraphNumCols><PlotInOneGraph NodeID="10" Label="Arrange Plots of Same Type in One Graph" DataID="4005" HandlerRC="564566720" DB_CTRL_ID="6123">0.</PlotInOneGraph></PlotSettings><RCSheet NodeID="13" Label="Fitted Results Sheet Arrangement" DataID="1559" Handler="564569536" Enable="1" DB_CTRL_ID="6125" Show="0">0.</RCSheet><DataIdentifier NodeID="268435456" Label="Dataset Identifier" DataID="313" Branch="2048" DataIDAssignDelay="6" DB_CTRL_ID="6127"><Identifier NodeID="11" Label="Identifier" OCntrlParam1="1" DataID="314" HandlerRC="564574528" DataIDAssignDelay="6" DB_CTRL_ID="6128"><![CDATA[Name]]></Identifier><CustomHint NodeID="11" Label="Custom Format: @D, @W, @LL[@LU] etc" DataID="317" Enable="2" DispFormat="16384" DataIDAssignDelay="6" DB_CTRL_ID="6130" Show="0"/><Custom NodeID="11" Label="Custom Identifier" DataID="315" DataIDAssignDelay="6" DB_CTRL_ID="6131" Show="0"/><FlatSheet NodeID="10" Label="Show Identifier in Flat Sheet" DataID="316" DataIDAssignDelay="6" DB_CTRL_ID="6133">0.</FlatSheet></DataIdentifier><Report NodeID="268435456" Label="Report Tables" DataID="2097166" Branch="2048" DB_CTRL_ID="6135"><Book NodeID="11" Label="Book" OCntrlParam1="1" DataID="907" Handler="564587712" ReportToSrcBook="1" old_combo_val="&lt;auto&gt;" DB_CTRL_ID="6136">&lt;auto&gt;</Book><BookName NodeID="11" Label="BookName" DataID="20000" HandlerRC="564589504" Default="LinearFit1" Enable="0" DB_CTRL_ID="6138">Book1</BookName><NameForNew NodeID="11" Label="" DataID="20001" Show="0" DB_CTRL_ID="6140"/><Sheet NodeID="11" Label="Sheet" OCntrlParam1="1" DataID="908" Handler="564593344" old_combo_val="&lt;new&gt;" DB_CTRL_ID="6142" Enable="0">&lt;new&gt;</Sheet><SheetName NodeID="11" Label="SheetName" DataID="20005" HandlerRC="564595136" Default="FitLinear1" Enable="1" DB_CTRL_ID="6144">FitLinear1</SheetName><NameForNew NodeID="11" Label="" DataID="20006" Show="0" DB_CTRL_ID="6146"/><AddReportToResultsLog NodeID="10" Label="Results Log" DataID="928" DB_CTRL_ID="6148">0.</AddReportToResultsLog><DumpScriptWindow NodeID="10" Label="Script Window" DataID="935" DB_CTRL_ID="6150">0.</DumpScriptWindow><DumpNotesWindow NodeID="11" Label="Notes Window" DataID="936" DB_CTRL_ID="6152">&lt;none&gt;</DumpNotesWindow></Report><Data NodeID="268435456" Label="Fitted Curves" DataID="2097164" Branch="2048" DB_CTRL_ID="6154"><Book NodeID="11" Label="Book" DataID="903" HandlerRC="564601280" Enable="1" old_combo_val="&lt;auto&gt;" DB_CTRL_ID="6155">&lt;auto&gt;</Book><BookName NodeID="11" Label="BookName" DataID="20010" HandlerRC="564601408" Default="FitCurve1" Enable="0" DB_CTRL_ID="6157">Book1</BookName><NameForNew NodeID="11" Label="" DataID="20011" Show="0" DB_CTRL_ID="6159"/><Sheet NodeID="11" Label="Sheet" DataID="904" HandlerRC="564601536" Enable="0" old_combo_val="&lt;new&gt;" DB_CTRL_ID="6161">&lt;new&gt;</Sheet><SheetName NodeID="11" Label="SheetName" DataID="20015" HandlerRC="564601664" Default="FitLinearCurve1" Enable="1" DB_CTRL_ID="6163">FitLinearCurve1</SheetName><NameForNew NodeID="11" Label="" DataID="20016" Show="0" DB_CTRL_ID="6165"/></Data><Residual NodeID="268435456" Label="Fit Residuals" DataID="2097165" DB_CTRL_ID="6167"><Book NodeID="11" Label="Book" OCntrlParam1="1" DataID="901" Handler="564606528" old_combo_val="&lt;fittedvalue&gt;" DB_CTRL_ID="6168">&lt;fittedvalue&gt;</Book><BookName NodeID="11" Label="BookName" DataID="20020" HandlerRC="564595136" Default="Residual1" Enable="0" DB_CTRL_ID="6170">Book1</BookName><NameForNew NodeID="11" Label="" DataID="20021" Show="0" DB_CTRL_ID="6172"/><Sheet NodeID="11" Label="Sheet" OCntrlParam1="1" DataID="902" Handler="564612672" old_combo_val="&lt;fittedvalue&gt;" DB_CTRL_ID="6174" Enable="1">&lt;fittedvalue&gt;</Sheet><SheetName NodeID="11" Label="SheetName" DataID="20025" HandlerRC="564595136" Default="FitLinearResiduals1" Enable="0" DB_CTRL_ID="6176">FitLinearCurve1</SheetName><NameForNew NodeID="11" Label="" DataID="20026" Show="0" DB_CTRL_ID="6178"/></Residual><FindXY NodeID="268435456" Label="Find Specific X/Y Tables" DataID="2097167" Handler="564616896" DB_CTRL_ID="6180" Enable="0" Branch="2"><Book NodeID="11" Label="Book" OCntrlParam1="1" DataID="926" Handler="564620096" old_combo_val="&lt;fittedvalue&gt;" DB_CTRL_ID="6181">&lt;fittedvalue&gt;</Book><BookName NodeID="11" Label="BookName" DataID="20030" HandlerRC="564595136" Default="FindXY1" Enable="0" DB_CTRL_ID="6183">Book1</BookName><NameForNew NodeID="11" Label="" DataID="20031" Show="0" DB_CTRL_ID="6185"/><Sheet NodeID="11" Label="Sheet" OCntrlParam1="1" DataID="927" Handler="564626240" old_combo_val="&lt;new&gt;" DB_CTRL_ID="6187" Enable="1">&lt;new&gt;</Sheet><SheetName NodeID="11" Label="FindX SheetName" DataID="20035" HandlerRC="564595136" Default="FitLinearFindXfromY1" Enable="1" DB_CTRL_ID="6189">FitLinearFindXfromY1</SheetName><NameForNew NodeID="11" Label="" DataID="20036" Show="0" DB_CTRL_ID="6191"/><SheetName2 NodeID="11" Label="FindY SheetName" DataID="20034" HandlerRC="564595136" Default="FitLinearFindYfromX1" Enable="1" DB_CTRL_ID="6193">FitLinearFindYfromX1</SheetName2><NameForNew NodeID="11" Label="" DataID="20037" Show="0" DB_CTRL_ID="6195"/></FindXY><Create NodeID="268435456" Label="Optional Report Tables" DataID="937" Branch="2623489" DB_CTRL_ID="6197"><Notes NodeID="10" Label="Notes" DataID="1500" DB_CTRL_ID="6198">1.</Notes><InputData NodeID="10" Label="Input Data" DataID="1505" DB_CTRL_ID="6200">1.</InputData><MaskedData NodeID="10" Label="Masked Data" DataID="1510" DB_CTRL_ID="6202">1</MaskedData><MissingData NodeID="10" Label="Missing Data" DataID="1515" DB_CTRL_ID="6204">1</MissingData></Create><KeepSessionGraph Show="0" DB_CTRL_ID="6206">0</KeepSessionGraph><OutManagerPointer DataID="20150" Show="0" ThemeApplicability="196608" DB_CTRL_ID="6208">309266928</OutManagerPointer><OperationPointer DataID="20155" Show="0" ThemeApplicability="196608" DB_CTRL_ID="6210">316364640</OperationPointer></Output><Graph1 NodeID="268435456" Label="Fitted Curves Plot" DataID="1520" Use="1" RepeatID="1" DB_CTRL_ID="6212"><DoPlot NodeID="10" Label="Plot in Report Table" DataID="256" Handler="564650816" DB_CTRL_ID="6213">1.</DoPlot><PlotType NodeID="13" Label="Plot Type" DataID="267" Handler="564657344" DB_CTRL_ID="6215" Show="0">0.</PlotType><PlotFit NodeID="13" Label="Plot on Source Graph" DataID="268" Handler="564668992" DB_CTRL_ID="6217" Enable="1">1</PlotFit><UpdateLegend NodeID="10" Label="Update Legend on Source Graph" DataID="269" DB_CTRL_ID="6219" Enable="1">1.</UpdateLegend><SetColor NodeID="10" Label="Multiple Plots Use Source Graph Color" DataID="276" HandlerRC="564672064" Enable="0" DB_CTRL_ID="6221" OldValue="1">1.</SetColor><XDataType NodeID="268435456" Label="X Data Type" DataID="300" Use="0" BranchCombo="Uniform Linear|Log|Same as Input Data|Use Source Graph Scale Type" Handler="564675392" Branch="1" DB_CTRL_ID="6223"><N NodeID="14" Label="Points" DataID="258" DB_CTRL_ID="6224" Enable="1">1000.</N><Range NodeID="13" Label="Range" DataID="305" Handler="564679232" DB_CTRL_ID="6226" Enable="1">0.</Range><Min NodeID="14" Label="Min" DataID="280" Auto="1" DB_CTRL_ID="6228" Enable="1" Show="0">0.</Min><Max NodeID="14" Label="Max" DataID="282" Auto="1" DB_CTRL_ID="6231" Show="0" Enable="1">10.</Max><RangeMargin NodeID="14" Label="Range Margin (%)" DataID="265" DB_CTRL_ID="6234" Show="1" Enable="1">0.</RangeMargin></XDataType><ConfBands NodeID="10" Label="Confidence Bands" DataID="271" HandlerRC="564685632" DB_CTRL_ID="6236">0.</ConfBands><PredBands NodeID="10" Label="Prediction Bands" DataID="272" HandlerRC="564685632" DB_CTRL_ID="6238">0.</PredBands><Confidence NodeID="14" Label="Confidence Level for Curves(%)" DataID="275" HandlerRC="564685632" DB_CTRL_ID="6240" Enable="0">95.</Confidence><Ellipse NodeID="268435456" Label="Ellipse" Use="0" DataID="306" DB_CTRL_ID="6242"><DataPoints NodeID="11" Label="Data Points" DataID="310" DB_CTRL_ID="6243">50</DataPoints><Mean NodeID="268435456" Label="Mean" Use="1" DataID="307" DB_CTRL_ID="6245"><confidence NodeID="11" Label="Confidence Level (%)" DataID="311" Handler="311981952" DB_CTRL_ID="6246">95</confidence></Mean><Pred NodeID="268435456" Label="Prediction" Use="1" DataID="309" DB_CTRL_ID="6248"><confidence NodeID="11" Label="Confidence Level (%)" DataID="312" Handler="311984896" DB_CTRL_ID="6249">95</confidence></Pred></Ellipse></Graph1><Calibration NodeID="268435456" Label="Find X/Y" DataID="2103296" DB_CTRL_ID="6251"><Custom2 NodeID="268435456" Label="Find X from Y" DataID="2103312" Use="0" RepeatID="2" Handler="564695232" DB_CTRL_ID="6252"><Cols NodeID="17" Label="Number of X Columns" DataID="1555" NumFormat="%d" Show="0" DB_CTRL_ID="6253">1.</Cols><Conf NodeID="10" Label="Calculate 95% Confidence Interval" DataID="1572" DB_CTRL_ID="6255">0.</Conf></Custom2><Custom3 NodeID="268435456" Label="Find Y from X" DataID="2103376" Use="0" RepeatID="3" Handler="564695232" DB_CTRL_ID="6257"><Cols NodeID="17" Label="Number of Y Columns" DataID="1555" NumFormat="%d" Show="0" DB_CTRL_ID="6258">1.</Cols><Conf NodeID="10" Label="Calculate 95% Confidence Interval" DataID="1572" DB_CTRL_ID="6260">0.</Conf></Custom3></Calibration><Residuals NodeID="268435456" Label="Residual Plots" DataID="1320" Branch="2621442" DB_CTRL_ID="6262"><ResType NodeID="13" Label="Residual Type" DataID="3950" DB_CTRL_ID="6263" Enable="0">0</ResType><Graph2 NodeID="10" Label="Residual vs. Independent Plot" DataID="1521" RepeatID="2" DB_CTRL_ID="6265">1</Graph2><Graph3 NodeID="10" Label="Histogram of the Residual Plot" DataID="1522" RepeatID="3" DB_CTRL_ID="6267">0</Graph3><Graph4 NodeID="10" Label="Residual vs. Predicted Values Plot" DataID="1523" RepeatID="4" DB_CTRL_ID="6269">0</Graph4><Graph5 NodeID="10" Label="Residual vs. the Order of the Data Plot" DataID="1524" RepeatID="5" DB_CTRL_ID="6271">0</Graph5><Graph6 NodeID="10" Label="Residual Lag Plot" DataID="1525" RepeatID="6" DB_CTRL_ID="6273">0</Graph6></Residuals><option Show="0" DB_CTRL_ID="6275">0</option></GUI>
